NiukeJishuGangBibeiBiMianshiSuanfaFix1/README.md
NiukeJishuGangBibeiBiMianshiSuanfaFix1/__init__.py
NiukeJishuGangBibeiBiMianshiSuanfaFix1/__main__.py
NiukeJishuGangBibeiBiMianshiSuanfaFix1/file.epub
NiukeJishuGangBibeiBiMianshiSuanfaFix1/index.html
NiukeJishuGangBibeiBiMianshiSuanfaFix1/css/__init__.py
NiukeJishuGangBibeiBiMianshiSuanfaFix1/css/annotations.css
NiukeJishuGangBibeiBiMianshiSuanfaFix1/css/main.css
NiukeJishuGangBibeiBiMianshiSuanfaFix1/css/normalize.css
NiukeJishuGangBibeiBiMianshiSuanfaFix1/css/popup.css
NiukeJishuGangBibeiBiMianshiSuanfaFix1/font/__init__.py
NiukeJishuGangBibeiBiMianshiSuanfaFix1/font/fontello.eot
NiukeJishuGangBibeiBiMianshiSuanfaFix1/font/fontello.svg
NiukeJishuGangBibeiBiMianshiSuanfaFix1/font/fontello.ttf
NiukeJishuGangBibeiBiMianshiSuanfaFix1/font/fontello.woff
NiukeJishuGangBibeiBiMianshiSuanfaFix1/img/__init__.py
NiukeJishuGangBibeiBiMianshiSuanfaFix1/img/annotator-glyph-sprite.png
NiukeJishuGangBibeiBiMianshiSuanfaFix1/img/annotator-icon-sprite.png
NiukeJishuGangBibeiBiMianshiSuanfaFix1/img/apple-touch-icon.png
NiukeJishuGangBibeiBiMianshiSuanfaFix1/img/cancelfullscreen.png
NiukeJishuGangBibeiBiMianshiSuanfaFix1/img/close.png
NiukeJishuGangBibeiBiMianshiSuanfaFix1/img/fullscreen.png
NiukeJishuGangBibeiBiMianshiSuanfaFix1/img/loader.gif
NiukeJishuGangBibeiBiMianshiSuanfaFix1/img/menu-icon.png
NiukeJishuGangBibeiBiMianshiSuanfaFix1/img/save.png
NiukeJishuGangBibeiBiMianshiSuanfaFix1/img/saved.png
NiukeJishuGangBibeiBiMianshiSuanfaFix1/img/settings-s.png
NiukeJishuGangBibeiBiMianshiSuanfaFix1/img/settings.png
NiukeJishuGangBibeiBiMianshiSuanfaFix1/img/star.png
NiukeJishuGangBibeiBiMianshiSuanfaFix1/js/__init__.py
NiukeJishuGangBibeiBiMianshiSuanfaFix1/js/epub.js
NiukeJishuGangBibeiBiMianshiSuanfaFix1/js/epub.min.js
NiukeJishuGangBibeiBiMianshiSuanfaFix1/js/epub.min.map
NiukeJishuGangBibeiBiMianshiSuanfaFix1/js/hooks.min.js
NiukeJishuGangBibeiBiMianshiSuanfaFix1/js/hooks.min.map
niuke_jishu_gang_bibei_bi_mianshi_suanfa_fix1-2025.3.25.0.dist-info/METADATA
niuke_jishu_gang_bibei_bi_mianshi_suanfa_fix1-2025.3.25.0.dist-info/WHEEL
niuke_jishu_gang_bibei_bi_mianshi_suanfa_fix1-2025.3.25.0.dist-info/entry_points.txt
niuke_jishu_gang_bibei_bi_mianshi_suanfa_fix1-2025.3.25.0.dist-info/top_level.txt
niuke_jishu_gang_bibei_bi_mianshi_suanfa_fix1-2025.3.25.0.dist-info/RECORD
